potatoscript/potatoPostgreSQL.py
potatoscript/test.py
potatoPostgreSQL-1.0.5.dist-info/METADATA
potatoPostgreSQL-1.0.5.dist-info/WHEEL
potatoPostgreSQL-1.0.5.dist-info/top_level.txt
potatoPostgreSQL-1.0.5.dist-info/RECORD
