Metadata-Version: 2.1
Name: potatoPostgreSQL
Version: 1.0.5
Summary: A simple library for connecting to PostgreSQL
Author: ks lim
Author-email: kianseng.lim@sony.com
